codetools/__init__.py
codetools/additional_todo.py
codetools/core.py
codetools/instance.py
codetools/main.py
codetools/tool_dict.py
codetools/tool_stats.py
codetools/utils.py
code_tools_agent-0.1.3.dist-info/LICENSE
code_tools_agent-0.1.3.dist-info/METADATA
code_tools_agent-0.1.3.dist-info/WHEEL
code_tools_agent-0.1.3.dist-info/RECORD
