Metadata-Version: 2.3
Name: code-tools-agent
Version: 0.1.3
Summary: A powerful framework for providing tools to AI agents with Docker/local deployment support
License: MIT
Keywords: artificial intelligence,ai agents,code tools,docker,swarms
Author: balajidinesh
Requires-Python: >=3.10,<4.0
Classifier: Development Status :: 4 - Beta
Classifier: Intended Audience :: Developers
Classifier: License :: OSI Approved :: MIT License
Classifier: Programming Language :: Python :: 3
Classifier: Programming Language :: Python :: 3.10
Classifier: Programming Language :: Python :: 3.11
Classifier: Programming Language :: Python :: 3.12
Classifier: Programming Language :: Python :: 3.13
Classifier: Programming Language :: Python :: 3.9
Classifier: Topic :: Scientific/Engineering :: Artificial Intelligence
Provides-Extra: examples
Requires-Dist: python-dotenv
Requires-Dist: swe-rex (>=1.3.0,<2.0.0)
Project-URL: Documentation, https://github.com/balajidinesh/code-tools
Project-URL: Homepage, https://github.com/balajidinesh/code-tools
Project-URL: Repository, https://github.com/balajidinesh/code-tools
